Metadata-Version: 1.2
Name: mreduce
Version: 0.0.13
Summary: MReduce python sdk
Home-page: https://mreduce.com
Author: MReduce
Author-email: support@mreduce.com
License: UNKNOWN
Platform: UNKNOWN
Requires-Python: >=2.7
